Metadata-Version: 2.1
Name: django-media-placeholder
Version: 0.1
Summary: Process every media request, if media not present locally, and try to obtain in another location
Home-page: https://github.com/shinneider/django_media_placeholder
Author: Shinneider Libanio da Silva
Author-email: shinneider-libanio@hotmail.com
License: MIT
Platform: UNKNOWN
Requires-Python: >=3.3
